filtered_toctree/__init__.py
filtered_toctree/_version.py
filtered_toctree/directive.py
filtered_toctree-0.0.1.dist-info/licenses/LICENSE
filtered_toctree-0.0.1.dist-info/METADATA
filtered_toctree-0.0.1.dist-info/WHEEL
filtered_toctree-0.0.1.dist-info/top_level.txt
filtered_toctree-0.0.1.dist-info/RECORD
